trytond/modules/health_ntd_dengue/COPYING
trytond/modules/health_ntd_dengue/README.rst
trytond/modules/health_ntd_dengue/__init__.py
trytond/modules/health_ntd_dengue/data/health_ntd_dengue_sequence.xml
trytond/modules/health_ntd_dengue/data/lab_test_data.xml
trytond/modules/health_ntd_dengue/health_ntd_dengue.py
trytond/modules/health_ntd_dengue/health_ntd_dengue_view.xml
trytond/modules/health_ntd_dengue/locale/ar.po
trytond/modules/health_ntd_dengue/locale/de.po
trytond/modules/health_ntd_dengue/locale/el.po
trytond/modules/health_ntd_dengue/locale/eo.po
trytond/modules/health_ntd_dengue/locale/es.po
trytond/modules/health_ntd_dengue/locale/fr.po
trytond/modules/health_ntd_dengue/locale/health_ntd_dengue.pot
trytond/modules/health_ntd_dengue/locale/it_IT.po
trytond/modules/health_ntd_dengue/locale/ja_JP.po
trytond/modules/health_ntd_dengue/locale/ka.po
trytond/modules/health_ntd_dengue/locale/lo.po
trytond/modules/health_ntd_dengue/locale/pt_BR.po
trytond/modules/health_ntd_dengue/locale/sv.po
trytond/modules/health_ntd_dengue/locale/tr.po
trytond/modules/health_ntd_dengue/locale/uk.po
trytond/modules/health_ntd_dengue/locale/zh_CN.po
trytond/modules/health_ntd_dengue/pyproject.toml
trytond/modules/health_ntd_dengue/sequences.py
trytond/modules/health_ntd_dengue/tests/__init__.py
trytond/modules/health_ntd_dengue/tests/test_health_ntd_dengue.py
trytond/modules/health_ntd_dengue/tryton.cfg
trytond/modules/health_ntd_dengue/view/gnuhealth_dengue_du_survey_form.xml
trytond/modules/health_ntd_dengue/view/gnuhealth_dengue_du_survey_tree.xml
gnuhealth_ntd_dengue-5.0.2.dist-info/METADATA
gnuhealth_ntd_dengue-5.0.2.dist-info/WHEEL
gnuhealth_ntd_dengue-5.0.2.dist-info/licenses/COPYING
gnuhealth_ntd_dengue-5.0.2.dist-info/RECORD
